{
  "battery": "Li-Po 4000 mAh, non-removable (15.2 Wh)",
  "battery_charging": "undefined",
  "battery_life": "undefined",
  "benchmarks": "undefined",
  "bluetooth": "4.1, LE",
  "body_build": "undefined",
  "body_dimensions": "203.2 x 134.5 x 6.9 mm (8.0 x 5.30 x 0.27 in)",
  "body_weight": "317 g (11.18 oz)",
  "chipset": "Intel Atom Z3530",
  "colors": "Black, White",
  "cpu": "Quad-core",
  "display_protection": "Oleophobic coating",
  "display_resolution": "1536 x 2048 pixels, 4:3 ratio (~320 ppi density)",
  "display_size": "8.0 inches, 198.2 cm2 (~72.5% screen-to-body ratio)",
  "display_type": "IPS LCD",
  "gps": "Yes, GLONASS",
  "gpu": "PowerVR G6430",
  "image_url": "https://fdn2.gsmarena.com/vv/bigpic/asus-zenpad-s-80.jpg",
  "infrared_port": "undefined",
  "internal_memory": "16GB 2GB RAM, 32GB 2GB RAM",
  "launch_date": "2015, June. Released 2015, August",
  "launch_status": "Discontinued",
  "loudspeaker": "Yes, with stereo speakers",
  "main_camera": "5 MP",
  "main_camera_features": "undefined",
  "main_camera_video": "Yes",
  "memory_slot": "microSDXC (dedicated slot)",
  "modelname": "Asus Zenpad S 8.0 Z580C",
  "models": "undefined",
  "network_3g_bands": "undefined",
  "network_4g_bands": "undefined",
  "network_5g_bands": "undefined",
  "network_speed": "undefined",
  "network_tech": "No cellular connectivity",
  "nfc": "No",
  "os": "Android 5.0 (Lollipop)",
  "price": "undefined",
  "radio": "No",
  "sar_eu": "undefined",
  "sar_us": "undefined",
  "selfie_camera": "2 MP",
  "selfie_camera_video": "",
  "sensors": "Accelerometer, compass",
  "sim_type": "No",
  "usb": "microUSB 2.0",
  "wlan": "Wi-Fi 802.11 a/b/g/n/ac"
}