{
  "battery": "Removable Li-Ion 1530 mAh battery",
  "battery_charging": "undefined",
  "battery_life": "undefined",
  "benchmarks": "undefined",
  "bluetooth": "2.0",
  "body_build": "undefined",
  "body_dimensions": "121 x 70 x 16.5 mm (4.76 x 2.76 x 0.65 in)",
  "body_weight": "188 g (6.63 oz)",
  "chipset": "undefined",
  "colors": "Silver",
  "cpu": "Marvell PXA270M 520 MHz",
  "display_protection": "undefined",
  "display_resolution": "240 x 320 pixels, 4:3 ratio (~114 ppi density)",
  "display_size": "3.5 inches, 37.9 cm2 (~44.8% screen-to-body ratio)",
  "display_type": "TFT resistive touchscreen, 65K colors",
  "gps": "Yes, SiRF Star III chipset",
  "gpu": "undefined",
  "image_url": "https://fdn2.gsmarena.com/vv/bigpic/asus-p550.jpg",
  "infrared_port": "undefined",
  "internal_memory": "256MB 64MB RAM",
  "launch_date": "2007, December. Released 2008",
  "launch_status": "Discontinued",
  "loudspeaker": "No",
  "main_camera": "2 MP",
  "main_camera_features": "undefined",
  "main_camera_video": "Yes",
  "memory_slot": "miniSD, miniSDHC",
  "modelname": "Asus P550",
  "models": "undefined",
  "network_3g_bands": "UMTS 2100",
  "network_4g_bands": "undefined",
  "network_5g_bands": "undefined",
  "network_speed": "Yes, 384 kbps",
  "network_tech": "GSM / UMTS",
  "nfc": "undefined",
  "os": "Microsoft Windows Mobile 6.0 Professional",
  "price": "About 220 EUR",
  "radio": "No",
  "sar_eu": "undefined",
  "sar_us": "undefined",
  "selfie_camera": "No",
  "selfie_camera_video": "undefined",
  "sensors": "",
  "sim_type": "Mini-SIM",
  "usb": "1.1",
  "wlan": "Wi-Fi 802.11 b/g"
}