{
  "battery": "Li-Po 3500 mAh, non-removable (13 Wh)",
  "battery_charging": "undefined",
  "battery_life": "undefined",
  "benchmarks": "undefined",
  "bluetooth": "4.0, A2DP",
  "body_build": "undefined",
  "body_dimensions": "189 x 108 x 9.5 mm (7.44 x 4.25 x 0.37 in)",
  "body_weight": "275 g (9.70 oz)",
  "chipset": "Mediatek MT8382V/W (28 nm)",
  "colors": "Black, White",
  "cpu": "Quad-core Cortex-A7",
  "display_protection": "Oleophobic coating",
  "display_resolution": "600 x 1024 pixels, 16:9 ratio (~170 ppi density)",
  "display_size": "7.0 inches, 137.9 cm2 (~67.6% screen-to-body ratio)",
  "display_type": "IPS LCD",
  "gps": "Yes, with A-GPS, GLONASS",
  "gpu": "Mali-400MP2",
  "image_url": "https://fdn2.gsmarena.com/vv/bigpic/asus-zenpad-c-70.jpg",
  "infrared_port": "undefined",
  "internal_memory": "8GB 1GB RAM, 16GB 1GB RAM",
  "launch_date": "2015, June. Released 2015, August",
  "launch_status": "Discontinued",
  "loudspeaker": "Yes",
  "main_camera": "5 MP",
  "main_camera_features": "undefined",
  "main_camera_video": "Yes",
  "memory_slot": "microSDXC (dedicated slot)",
  "modelname": "Asus Zenpad C 7.0 Z170MG",
  "models": "undefined",
  "network_3g_bands": "HSDPA 900 / 2100",
  "network_4g_bands": "undefined",
  "network_5g_bands": "undefined",
  "network_speed": "HSPA 21.1/11.5 Mbps",
  "network_tech": "GSM / HSPA",
  "nfc": "No",
  "os": "Android 5.0 (Lollipop)",
  "price": "undefined",
  "radio": "No",
  "sar_eu": "undefined",
  "sar_us": "undefined",
  "selfie_camera": "VGA",
  "selfie_camera_video": "",
  "sensors": "Accelerometer",
  "sim_type": "Micro-SIM",
  "usb": "microUSB 2.0",
  "wlan": "Wi-Fi 802.11 b/g/n, hotspot"
}