{
  "battery": "Li-Ion 4000 mAh, non-removable",
  "battery_charging": "Fast charging 30W Quick Charge 4+",
  "battery_life": "Endurance rating 69h",
  "benchmarks": "AnTuTu: 288821 (v7) GeekBench: 9406 (v4.4) GFXBench: 31fps (ES 3.1 onscreen)",
  "bluetooth": "5.0, A2DP, LE, aptX HD",
  "body_build": "Glass front (Gorilla Glass 6), glass back (Gorilla Glass 5), aluminum frame",
  "body_dimensions": "158.8 x 76.2 x 8.3 mm (6.25 x 3.00 x 0.33 in)",
  "body_weight": "200 g (7.05 oz)",
  "chipset": "Qualcomm SDM845 Snapdragon 845 (10 nm)",
  "colors": "Black",
  "cpu": "Octa-core (4x2.96 GHz Kryo 385 Gold & 4x1.7 GHz Kryo 385 Silver)",
  "display_protection": "Corning Gorilla Glass 6",
  "display_resolution": "1080 x 2160 pixels, 18:9 ratio (~402 ppi density)",
  "display_size": "6.0 inches, 92.9 cm2 (~76.8% screen-to-body ratio)",
  "display_type": "AMOLED, 90Hz, HDR",
  "gps": "Yes, with A-GPS, GLONASS, BDS, GALILEO, QZSS",
  "gpu": "Adreno 630",
  "image_url": "https://fdn2.gsmarena.com/vv/bigpic/asus-rog-phone.jpg",
  "infrared_port": "undefined",
  "internal_memory": "128GB 8GB RAM, 512GB 8GB RAM",
  "launch_date": "2018, June",
  "launch_status": "Available. Released 2018, October",
  "loudspeaker": "Yes, with stereo speakers",
  "main_camera": "12 MP, f/1.8, 24mm (wide), 1/2.55\", 1.4\u00b5m, dual pixel PDAF, 4-axis OIS 8 MP, 12mm (ultrawide), no AF",
  "main_camera_features": "LED flash, panorama, HDR",
  "main_camera_video": "4K@30/60fps, 1080p@30/60/240fps, (3-axis gyro-EIS)",
  "memory_slot": "No",
  "modelname": "Asus ROG Phone ZS600KL",
  "models": "Z01QD, ZS600KL",
  "network_3g_bands": "HSDPA 800 / 850 / 900 / 1700(AWS) / 1800 / 1900 / 2100 - A version, B version",
  "network_4g_bands": "1, 2, 3, 4, 5, 7, 8, 12, 13, 17, 18, 19, 20, 28, 29, 32, 34, 38, 39, 40, 41, 46 - A version, B version",
  "network_5g_bands": "undefined",
  "network_speed": "HSPA 42.2/5.76 Mbps, LTE-A (5CA) Cat18 1200/150 Mbps",
  "network_tech": "GSM / CDMA / HSPA / LTE",
  "nfc": "Yes",
  "os": "Android 8.1 (Oreo), upgradable to Android 9.0 (Pie), ROG Gaming X UI",
  "price": "$\u2009559.99",
  "radio": "FM radio",
  "sar_eu": "undefined",
  "sar_us": "undefined",
  "selfie_camera": "8 MP, f/2.0, 24mm (wide)",
  "selfie_camera_video": "1080p@30fps",
  "sensors": "Fingerprint (rear-mounted), accelerometer, gyro, proximity, compass",
  "sim_type": "Dual SIM (Nano-SIM, dual stand-by)",
  "usb": "USB Type-C 3.1, accessory connector",
  "wlan": "Wi-Fi 802.11 a/b/g/n/ac/ad, dual-band, Wi-Fi Direct, hotspot"
}