{
  "battery": "Li-Po 6190 mAh, non-removable",
  "battery_charging": "undefined",
  "battery_life": "undefined",
  "benchmarks": "undefined",
  "bluetooth": "4.1, A2DP, LE",
  "body_build": "undefined",
  "body_dimensions": "200.4 x 132.6 x 7 mm (7.89 x 5.22 x 0.28 in)",
  "body_weight": "322 g (11.36 oz)",
  "chipset": "Intel Atom X5-Z8500",
  "colors": "Dark grey, Champagne gold",
  "cpu": "Quad-core 2.24 GHz",
  "display_protection": "undefined",
  "display_resolution": "1536 x 2048 pixels, 4:3 ratio (~326 ppi density)",
  "display_size": "7.9 inches, 190.9 cm2 (~71.8% screen-to-body ratio)",
  "display_type": "IPS LCD",
  "gps": "No",
  "gpu": "Intel HD Graphics",
  "image_url": "https://fdn2.gsmarena.com/vv/bigpic/xiaomi-mi-pad-2.jpg",
  "infrared_port": "undefined",
  "internal_memory": "16GB 2GB RAM, 64GB 2GB RAM",
  "launch_date": "2015, November. Released 2015, November",
  "launch_status": "Discontinued",
  "loudspeaker": "Yes, with stereo speakers",
  "main_camera": "8 MP, f/2.0",
  "main_camera_features": "undefined",
  "main_camera_video": "1080p@30fps",
  "memory_slot": "No",
  "modelname": "Xiaomi Mi Pad 2",
  "models": "undefined",
  "network_3g_bands": "undefined",
  "network_4g_bands": "undefined",
  "network_5g_bands": "undefined",
  "network_speed": "undefined",
  "network_tech": "No cellular connectivity",
  "nfc": "No",
  "os": "Android OS/ Optional Windows 10 (64 GB model), MIUI 7",
  "price": "About 180 EUR",
  "radio": "No",
  "sar_eu": "undefined",
  "sar_us": "undefined",
  "selfie_camera": "5 MP",
  "selfie_camera_video": "",
  "sensors": "Accelerometer, gyro, compass",
  "sim_type": "No",
  "usb": "USB Type-C",
  "wlan": "Wi-Fi 802.11 a/b/g/n/ac, dual-band, Wi-Fi Direct, hotspot"
}